adata_sdk/__init__.py
anndata_sdk-0.0.0.dist-info/LICENSE
anndata_sdk-0.0.0.dist-info/METADATA
anndata_sdk-0.0.0.dist-info/WHEEL
anndata_sdk-0.0.0.dist-info/top_level.txt
anndata_sdk-0.0.0.dist-info/RECORD
